auron/__init__.py
auron/__main__.py
auron/compress.py
auron/docopt.py
auron/edge_labels.py
auron/filters.py
auron/graph.py
auron/inductors.py
auron/label_base.py
auron/masternodes.py
auron/mesh.py
auron/netlist.py
auron/overdrive.py
auron/pin_labels.py
auron/surface_labels.py
auron/tools.py
auron/version.py
auron-1.0.4.dist-info/METADATA
auron-1.0.4.dist-info/RECORD
auron-1.0.4.dist-info/WHEEL
auron-1.0.4.dist-info/entry_points.txt
auron-1.0.4.dist-info/top_level.txt
