Metadata-Version: 2.1
Name: auron
Version: 1.0.4
Summary: UNKNOWN
Home-page: https://github.com/rubenvanstaden/auron
Author: Ruben van Staden
Author-email: rubenvanstaden@gmail.com
License: BSD
Keywords: auron
Platform: UNKNOWN
Requires-Dist: gdspy
Requires-Dist: yuna
Requires-Dist: shapely
Requires-Dist: networkx
Requires-Dist: docopt
Requires-Dist: pyclipper
Requires-Dist: pygmsh
Requires-Dist: pandoc
Requires-Dist: meshio
Requires-Dist: scipy
Requires-Dist: termcolor
Requires-Dist: plotly
Requires-Dist: pytest
